{
  "designation": "M1419W",
  "manufacturer": "AeroTech",
  "diameter": 9.800000000000001e-05,
  "length": 0.000579,
  "total_mass": 0.0,
  "propellant_mass": 0.0,
  "case_mass": 0.0,
  "burn_time": 7.0,
  "total_impulse": 7582.663500000001,
  "avg_thrust": 1083.2376428571429,
  "max_thrust": 1462.23,
  "thrust_curve": [
    [
      0.0,
      0.0
    ],
    [
      0.0,
      0.22
    ],
    [
      0.1,
      1307.13
    ],
    [
      0.2,
      1218.53
    ],
    [
      1.4,
      1373.59
    ],
    [
      2.5,
      1462.23
    ],
    [
      3.0,
      1440.04
    ],
    [
      3.6,
      1404.63
    ],
    [
      4.4,
      1160.84
    ],
    [
      5.8,
      664.66
    ],
    [
      6.1,
      629.17
    ],
    [
      6.5,
      177.25
    ],
    [
      6.9,
      8.9
    ],
    [
      7.0,
      0.0
    ]
  ],
  "delays": [],
  "url": "https://www.thrustcurve.org/motors/5f4294d200023100000001a8.html"
}