{
  "designation": "H112J",
  "manufacturer": "AeroTech",
  "diameter": 3.8e-05,
  "length": 0.000191,
  "total_mass": 0.0,
  "propellant_mass": 0.0,
  "case_mass": 0.0,
  "burn_time": 3.323,
  "total_impulse": 257.9613995,
  "avg_thrust": 77.62906996689739,
  "max_thrust": 104.922,
  "thrust_curve": [
    [
      0.064,
      85.431
    ],
    [
      0.194,
      101.938
    ],
    [
      0.324,
      101.897
    ],
    [
      0.454,
      102.839
    ],
    [
      0.584,
      104.479
    ],
    [
      0.715,
      103.845
    ],
    [
      0.845,
      103.439
    ],
    [
      0.975,
      104.286
    ],
    [
      1.106,
      104.922
    ],
    [
      1.236,
      104.39
    ],
    [
      1.367,
      102.768
    ],
    [
      1.497,
      102.237
    ],
    [
      1.627,
      100.032
    ],
    [
      1.757,
      98.345
    ],
    [
      1.888,
      94.56
    ],
    [
      2.018,
      89.018
    ],
    [
      2.148,
      82.857
    ],
    [
      2.279,
      77.685
    ],
    [
      2.409,
      72.373
    ],
    [
      2.54,
      67.041
    ],
    [
      2.67,
      59.764
    ],
    [
      2.8,
      37.616
    ],
    [
      2.93,
      14.457
    ],
    [
      3.06,
      4.642
    ],
    [
      3.192,
      1.818
    ],
    [
      3.323,
      0.0
    ]
  ],
  "delays": [],
  "url": "https://www.thrustcurve.org/motors/5f4294d2000231000000007e.html"
}