{
  "designation": "2304K815-P",
  "manufacturer": "Cesaroni Technology",
  "diameter": 5.4e-05,
  "length": 0.0006490000000000001,
  "total_mass": 0.0,
  "propellant_mass": 0.0,
  "case_mass": 0.0,
  "burn_time": 2.85,
  "total_impulse": 2302.175,
  "avg_thrust": 807.780701754386,
  "max_thrust": 1200.0,
  "thrust_curve": [
    [
      0.01,
      400.0
    ],
    [
      0.015,
      600.0
    ],
    [
      0.02,
      1200.0
    ],
    [
      0.05,
      620.0
    ],
    [
      0.07,
      720.0
    ],
    [
      0.1,
      825.0
    ],
    [
      0.3,
      910.0
    ],
    [
      1.0,
      945.0
    ],
    [
      1.5,
      970.0
    ],
    [
      1.8,
      970.0
    ],
    [
      2.12,
      930.0
    ],
    [
      2.3,
      650.0
    ],
    [
      2.43,
      640.0
    ],
    [
      2.58,
      300.0
    ],
    [
      2.7,
      150.0
    ],
    [
      2.85,
      0.0
    ]
  ],
  "delays": [],
  "url": "https://www.thrustcurve.org/motors/5f4294d200023100000002b7.html"
}