{
  "designation": "273H225-14A",
  "manufacturer": "Cesaroni Technology",
  "diameter": 3.8e-05,
  "length": 0.000186,
  "total_mass": 0.0,
  "propellant_mass": 0.0,
  "case_mass": 0.0,
  "burn_time": 1.21,
  "total_impulse": 273.85148728073494,
  "avg_thrust": 226.32354320721896,
  "max_thrust": 263.79,
  "thrust_curve": [
    [
      0.0,
      0.0
    ],
    [
      0.00262467,
      263.79
    ],
    [
      0.023622,
      246.549
    ],
    [
      0.0341207,
      234.48
    ],
    [
      0.0419948,
      219.825
    ],
    [
      0.0971129,
      237.066
    ],
    [
      0.136483,
      242.238
    ],
    [
      0.2021,
      242.238
    ],
    [
      0.272966,
      242.238
    ],
    [
      0.330709,
      241.376
    ],
    [
      0.377953,
      243.101
    ],
    [
      0.44357,
      243.101
    ],
    [
      0.503937,
      242.238
    ],
    [
      0.569554,
      241.376
    ],
    [
      0.635171,
      240.514
    ],
    [
      0.721785,
      238.79
    ],
    [
      0.821522,
      237.066
    ],
    [
      0.900262,
      234.48
    ],
    [
      0.968504,
      227.583
    ],
    [
      1.03675,
      221.549
    ],
    [
      1.06824,
      217.239
    ],
    [
      1.11811,
      206.032
    ],
    [
      1.13123,
      196.549
    ],
    [
      1.14173,
      216.377
    ],
    [
      1.15223,
      153.446
    ],
    [
      1.1601,
      103.447
    ],
    [
      1.1706,
      52.5856
    ],
    [
      1.18898,
      19.8273
    ],
    [
      1.21,
      0.0
    ]
  ],
  "delays": [],
  "url": "https://www.thrustcurve.org/motors/5f4294d20002310000000219.html"
}