{
  "designation": "1990K490-16A",
  "manufacturer": "Cesaroni Technology",
  "diameter": 5.4e-05,
  "length": 0.000488,
  "total_mass": 0.0,
  "propellant_mass": 0.0,
  "case_mass": 0.0,
  "burn_time": 4.066,
  "total_impulse": 1987.7223645,
  "avg_thrust": 488.8643296851943,
  "max_thrust": 593.796,
  "thrust_curve": [
    [
      0.0,
      0.0
    ],
    [
      0.013,
      445.79
    ],
    [
      0.024,
      376.662
    ],
    [
      0.083,
      559.232
    ],
    [
      0.121,
      584.047
    ],
    [
      0.316,
      573.412
    ],
    [
      0.727,
      569.867
    ],
    [
      1.116,
      553.914
    ],
    [
      1.875,
      522.009
    ],
    [
      1.893,
      593.796
    ],
    [
      1.944,
      519.35
    ],
    [
      2.658,
      479.468
    ],
    [
      3.063,
      473.264
    ],
    [
      3.358,
      444.018
    ],
    [
      3.618,
      448.449
    ],
    [
      3.894,
      240.177
    ],
    [
      4.055,
      31.019
    ],
    [
      4.066,
      0.0
    ]
  ],
  "delays": [],
  "url": "https://www.thrustcurve.org/motors/5f4294d20002310000000372.html"
}