{
  "designation": "2330K2000-P",
  "manufacturer": "Cesaroni Technology",
  "diameter": 7.5e-05,
  "length": 0.00035,
  "total_mass": 0.0,
  "propellant_mass": 0.0,
  "case_mass": 0.0,
  "burn_time": 1.191,
  "total_impulse": 2321.5905694999997,
  "avg_thrust": 1949.27839588581,
  "max_thrust": 2473.684,
  "thrust_curve": [
    [
      0.01,
      1979.532
    ],
    [
      0.029,
      1634.503
    ],
    [
      0.161,
      1947.368
    ],
    [
      0.321,
      2190.058
    ],
    [
      0.457,
      2397.661
    ],
    [
      0.548,
      2473.684
    ],
    [
      0.678,
      2383.041
    ],
    [
      0.768,
      2263.158
    ],
    [
      0.977,
      1923.977
    ],
    [
      1.027,
      1883.041
    ],
    [
      1.104,
      859.649
    ],
    [
      1.149,
      87.719
    ],
    [
      1.191,
      0.0
    ]
  ],
  "delays": [],
  "url": "https://www.thrustcurve.org/motors/5f4294d200023100000003d7.html"
}