{
  "designation": "HP-J425R",
  "manufacturer": "AeroTech",
  "diameter": 3.8e-05,
  "length": 0.000356,
  "total_mass": 0.0,
  "propellant_mass": 0.0,
  "case_mass": 0.0,
  "burn_time": 1.648,
  "total_impulse": 676.8332624999999,
  "avg_thrust": 410.6997952063107,
  "max_thrust": 452.851,
  "thrust_curve": [
    [
      0.0,
      0.0
    ],
    [
      0.018,
      267.857
    ],
    [
      0.062,
      368.062
    ],
    [
      0.242,
      420.092
    ],
    [
      0.524,
      443.216
    ],
    [
      0.902,
      452.851
    ],
    [
      1.225,
      448.997
    ],
    [
      1.389,
      433.581
    ],
    [
      1.502,
      452.851
    ],
    [
      1.53,
      420.092
    ],
    [
      1.542,
      356.5
    ],
    [
      1.599,
      67.446
    ],
    [
      1.618,
      28.905
    ],
    [
      1.648,
      0.0
    ]
  ],
  "delays": [],
  "url": "https://www.thrustcurve.org/motors/5f4294d20002310000000408.html"
}